newton_polynomial/__init__.py
newton_polynomial-1.0.1.dist-info/LICENSE
newton_polynomial-1.0.1.dist-info/METADATA
newton_polynomial-1.0.1.dist-info/WHEEL
newton_polynomial-1.0.1.dist-info/top_level.txt
newton_polynomial-1.0.1.dist-info/RECORD
