Metadata-Version: 2.1
Name: newton-polynomial
Version: 1.0.1
Summary: Newton Polynomial Interpolation
Home-page: https://github.com/msom/newton-polynomial
Author: Marc Sommerhalder
Author-email: msom@gmx.ch
License: UNKNOWN
Project-URL: Bug Tracker, https://github.com/msom/newton-polynomial/issues
Platform: UNKNOWN
Classifier: Programming Language :: Python :: 3
Classifier: License :: OSI Approved :: MIT License
Classifier: Operating System :: OS Independent
Requires-Python: >=3.6
Requires-Dist: numpy
Requires-Dist: sympy
